{
  "profiles": [
    {
      "id": "desert",
      "name": "Desert",
      "description": "Endless dunes of crystalline sand stretch toward the horizon",
      "environmental_features": [
        {
          "feature_type": "glass_dune",
          "weight": 30,
          "description_template": "A dune of fused glass catches the light",
          "mechanical_effects": {
            "visibility_modifier": 0.8,
            "movement_cost": 1.2
          }
        },
        {
          "feature_type": "salt_outcrop",
          "weight": 25,
          "description_template": "Salt crystals jut from the sand like broken teeth",
          "mechanical_effects": {
            "damage_per_turn": 1
          }
        },
        {
          "feature_type": "mirage_shimmer",
          "weight": 20,
          "description_template": "Heat mirages dance across the sand",
          "mechanical_effects": {
            "visibility_modifier": 0.6
          }
        },
        {
          "feature_type": "wind_carved_stone",
          "weight": 15,
          "description_template": "Ancient stone worn smooth by endless winds",
          "mechanical_effects": null
        },
        {
          "feature_type": "buried_relic",
          "weight": 10,
          "description_template": "Something metallic glints beneath the sand",
          "mechanical_effects": null
        }
      ],
      "atmospheric_elements": [
        {
          "element_type": "heat_shimmer",
          "intensity": 0.7,
          "description": "The air shimmers with oppressive heat.",
          "triggers": ["day", "storm"]
        },
        {
          "element_type": "wind_whistle",
          "intensity": 0.5,
          "description": "Wind whistles through hidden crevices.",
          "triggers": ["night", "storm"]
        },
        {
          "element_type": "glass_chime",
          "intensity": 0.3,
          "description": "Distant glass fragments chime in the breeze.",
          "triggers": ["storm", "adapted"]
        }
      ],
      "hazards": [
        {
          "hazard_type": "heat_exhaustion",
          "severity": 4,
          "frequency": 0.3,
          "description": "The relentless sun saps your strength",
          "damage_type": "heat"
        },
        {
          "hazard_type": "sandstorm",
          "severity": 6,
          "frequency": 0.2,
          "description": "Stinging sand reduces visibility to nothing",
          "damage_type": "environmental"
        }
      ],
      "resource_modifiers": {
        "water_multiplier": 0.3,
        "glass_multiplier": 1.2,
        "salt_multiplier": 0.8,
        "rare_materials_chance": 0.4
      },
      "story_themes": [
        "ancient_ruins",
        "lost_travelers",
        "desert_mysteries"
      ],
      "ambient_descriptions": {
        "entries": [
          {"item": "The desert stretches endlessly, glass and sand merged by ancient storms.", "weight": 3},
          {"item": "Crystalline dunes shift and flow like frozen waves.", "weight": 3},
          {"item": "The horizon wavers in the heat, reality bending like light through glass.", "weight": 2},
          {"item": "Salt-crusted sand crunches beneath your feet.", "weight": 2},
          {"item": "The silence is broken only by the whisper of wind through glass.", "weight": 1}
        ]
      }
    },
    {
      "id": "saltflat",
      "name": "Saltflat",
      "description": "Vast expanses of crystallized salt stretch like a frozen sea",
      "environmental_features": [
        {
          "feature_type": "salt_crystal_formation",
          "weight": 35,
          "description_template": "Towering salt crystals form natural spires",
          "mechanical_effects": {
            "visibility_modifier": 1.2
          }
        },
        {
          "feature_type": "brine_pool",
          "weight": 25,
          "description_template": "A pool of concentrated brine reflects the sky",
          "mechanical_effects": {
            "damage_per_turn": 2,
            "status_effect": "salt_burn"
          }
        },
        {
          "feature_type": "salt_maze",
          "weight": 20,
          "description_template": "Walls of salt create a natural labyrinth",
          "mechanical_effects": {
            "movement_cost": 1.5
          }
        },
        {
          "feature_type": "preserved_remains",
          "weight": 15,
          "description_template": "Something ancient lies preserved in salt",
          "mechanical_effects": null
        },
        {
          "feature_type": "salt_garden",
          "weight": 5,
          "description_template": "Delicate salt formations bloom like flowers",
          "mechanical_effects": null
        }
      ],
      "atmospheric_elements": [
        {
          "element_type": "salt_wind",
          "intensity": 0.8,
          "description": "Salt-laden wind stings your eyes and throat.",
          "triggers": ["day", "storm"]
        },
        {
          "element_type": "crystal_resonance",
          "intensity": 0.4,
          "description": "The salt crystals hum with an otherworldly tone.",
          "triggers": ["storm", "adapted"]
        },
        {
          "element_type": "brine_mist",
          "intensity": 0.6,
          "description": "Caustic mist rises from hidden pools.",
          "triggers": ["night"]
        }
      ],
      "hazards": [
        {
          "hazard_type": "salt_burn",
          "severity": 5,
          "frequency": 0.4,
          "description": "Caustic salt crystals burn exposed skin",
          "damage_type": "chemical"
        },
        {
          "hazard_type": "dehydration",
          "severity": 7,
          "frequency": 0.5,
          "description": "The salt draws moisture from your body",
          "damage_type": "environmental"
        }
      ],
      "resource_modifiers": {
        "water_multiplier": 0.1,
        "glass_multiplier": 0.8,
        "salt_multiplier": 2.5,
        "rare_materials_chance": 0.6
      },
      "story_themes": [
        "salt_preservation",
        "ancient_seas",
        "crystalline_visions"
      ],
      "ambient_descriptions": {
        "entries": [
          {"item": "The salt flats stretch like a frozen ocean, white as bone.", "weight": 3},
          {"item": "Crystalline formations catch and scatter light in rainbow patterns.", "weight": 3},
          {"item": "The air tastes of brine and ancient seas.", "weight": 2},
          {"item": "Salt crystals crunch and sing beneath your steps.", "weight": 2},
          {"item": "Preserved in salt, the past refuses to decay.", "weight": 1}
        ]
      }
    },
    {
      "id": "scrubland",
      "name": "Scrubland",
      "description": "Hardy vegetation clings to life among glass-sharp thorns",
      "environmental_features": [
        {
          "feature_type": "thorn_thicket",
          "weight": 30,
          "description_template": "Dense thickets of glass-sharp thorns block the way",
          "mechanical_effects": {
            "movement_cost": 2.0,
            "damage_per_turn": 1
          }
        },
        {
          "feature_type": "crystal_cactus",
          "weight": 25,
          "description_template": "Cacti with crystalline spines store precious water",
          "mechanical_effects": null
        },
        {
          "feature_type": "spider_web_grove",
          "weight": 20,
          "description_template": "Webs of glass fiber stretch between twisted trees",
          "mechanical_effects": {
            "visibility_modifier": 0.7
          }
        },
        {
          "feature_type": "root_network",
          "weight": 15,
          "description_template": "Exposed roots form a network of natural bridges",
          "mechanical_effects": {
            "movement_cost": 0.8
          }
        },
        {
          "feature_type": "bloom_cluster",
          "weight": 10,
          "description_template": "Rare flowers bloom in defiance of the harsh land",
          "mechanical_effects": null
        }
      ],
      "atmospheric_elements": [
        {
          "element_type": "thorn_rustle",
          "intensity": 0.6,
          "description": "Thorns rustle with hidden movement.",
          "triggers": ["day", "night"]
        },
        {
          "element_type": "web_glint",
          "intensity": 0.4,
          "description": "Spider webs catch the light like scattered diamonds.",
          "triggers": ["day", "adapted"]
        },
        {
          "element_type": "root_whisper",
          "intensity": 0.3,
          "description": "The root network seems to whisper secrets.",
          "triggers": ["night", "storm"]
        }
      ],
      "hazards": [
        {
          "hazard_type": "thorn_laceration",
          "severity": 3,
          "frequency": 0.6,
          "description": "Glass-sharp thorns tear at your clothing and skin",
          "damage_type": "piercing"
        },
        {
          "hazard_type": "web_entanglement",
          "severity": 4,
          "frequency": 0.3,
          "description": "Sticky webs slow your movement",
          "damage_type": "restraint"
        }
      ],
      "resource_modifiers": {
        "water_multiplier": 0.7,
        "glass_multiplier": 1.1,
        "salt_multiplier": 0.6,
        "rare_materials_chance": 0.5
      },
      "story_themes": [
        "nature_adaptation",
        "hidden_paths",
        "survival_wisdom"
      ],
      "ambient_descriptions": {
        "entries": [
          {"item": "Twisted vegetation clings to life in the harsh scrubland.", "weight": 3},
          {"item": "Glass-sharp thorns glitter like deadly jewels.", "weight": 3},
          {"item": "The scent of hardy blooms mingles with dust and danger.", "weight": 2},
          {"item": "Spider webs span the gaps between gnarled branches.", "weight": 2},
          {"item": "Life finds a way, even in this crystalline wasteland.", "weight": 1}
        ]
      }
    },
    {
      "id": "oasis",
      "name": "Oasis",
      "description": "A rare sanctuary where water and life flourish",
      "environmental_features": [
        {
          "feature_type": "spring_pool",
          "weight": 35,
          "description_template": "Clear water bubbles up from hidden depths",
          "mechanical_effects": null
        },
        {
          "feature_type": "palm_grove",
          "weight": 25,
          "description_template": "Date palms provide blessed shade",
          "mechanical_effects": {
            "visibility_modifier": 0.8
          }
        },
        {
          "feature_type": "flowering_garden",
          "weight": 20,
          "description_template": "Vibrant flowers bloom in impossible profusion",
          "mechanical_effects": null
        },
        {
          "feature_type": "crystal_spring",
          "weight": 15,
          "description_template": "Water flows over beds of pure crystal",
          "mechanical_effects": null
        },
        {
          "feature_type": "meditation_circle",
          "weight": 5,
          "description_template": "Stones arranged in perfect harmony invite contemplation",
          "mechanical_effects": null
        }
      ],
      "atmospheric_elements": [
        {
          "element_type": "water_music",
          "intensity": 0.8,
          "description": "The gentle sound of flowing water soothes the spirit.",
          "triggers": ["day", "night"]
        },
        {
          "element_type": "bird_song",
          "intensity": 0.6,
          "description": "Rare birds sing from hidden perches.",
          "triggers": ["day"]
        },
        {
          "element_type": "flower_perfume",
          "intensity": 0.5,
          "description": "Sweet floral scents drift on the breeze.",
          "triggers": ["day", "night"]
        }
      ],
      "hazards": [
        {
          "hazard_type": "territorial_guardian",
          "severity": 6,
          "frequency": 0.2,
          "description": "Something guards this precious sanctuary",
          "damage_type": "combat"
        },
        {
          "hazard_type": "false_paradise",
          "severity": 4,
          "frequency": 0.1,
          "description": "Not all oases are what they seem",
          "damage_type": "psychic"
        }
      ],
      "resource_modifiers": {
        "water_multiplier": 3.0,
        "glass_multiplier": 0.5,
        "salt_multiplier": 0.3,
        "rare_materials_chance": 0.8
      },
      "story_themes": [
        "sanctuary_refuge",
        "hidden_wisdom",
        "natural_harmony"
      ],
      "ambient_descriptions": {
        "entries": [
          {"item": "A blessed oasis blooms in defiance of the wasteland.", "weight": 3},
          {"item": "Clear water reflects the sky like a mirror of hope.", "weight": 3},
          {"item": "The air is sweet with the scent of impossible flowers.", "weight": 2},
          {"item": "Palm fronds whisper secrets in the gentle breeze.", "weight": 2},
          {"item": "Here, life remembers what it was before the storms.", "weight": 1}
        ]
      }
    },
    {
      "id": "ruins",
      "name": "Ruins",
      "description": "Shattered remnants of the world that was, fused by glass storms",
      "environmental_features": [
        {
          "feature_type": "glass_fused_building",
          "weight": 30,
          "description_template": "Ancient structures melted and reformed by storm glass",
          "mechanical_effects": {
            "visibility_modifier": 1.1
          }
        },
        {
          "feature_type": "archive_terminal",
          "weight": 25,
          "description_template": "A dormant data terminal waits in the shadows",
          "mechanical_effects": null
        },
        {
          "feature_type": "refraction_chamber",
          "weight": 20,
          "description_template": "A room where light bends in impossible ways",
          "mechanical_effects": {
            "visibility_modifier": 0.5,
            "status_effect": "disorientation"
          }
        },
        {
          "feature_type": "scripture_wall",
          "weight": 15,
          "description_template": "Ancient text carved into glass-fused stone",
          "mechanical_effects": null
        },
        {
          "feature_type": "memory_echo",
          "weight": 10,
          "description_template": "Ghostly images flicker in the crystalline walls",
          "mechanical_effects": {
            "status_effect": "vision"
          }
        }
      ],
      "atmospheric_elements": [
        {
          "element_type": "data_whisper",
          "intensity": 0.5,
          "description": "Fragments of old data streams whisper in the walls.",
          "triggers": ["adapted", "storm"]
        },
        {
          "element_type": "glass_harmony",
          "intensity": 0.4,
          "description": "The fused structures resonate with harmonic frequencies.",
          "triggers": ["storm", "night"]
        },
        {
          "element_type": "memory_flicker",
          "intensity": 0.3,
          "description": "Ghostly images of the past flicker in reflective surfaces.",
          "triggers": ["adapted"]
        }
      ],
      "hazards": [
        {
          "hazard_type": "structural_collapse",
          "severity": 8,
          "frequency": 0.3,
          "description": "Weakened structures threaten to collapse",
          "damage_type": "crushing"
        },
        {
          "hazard_type": "data_corruption",
          "severity": 5,
          "frequency": 0.2,
          "description": "Corrupted data streams assault your mind",
          "damage_type": "psychic"
        },
        {
          "hazard_type": "refraction_trap",
          "severity": 6,
          "frequency": 0.25,
          "description": "Light bends in ways that confuse and disorient",
          "damage_type": "disorientation"
        }
      ],
      "resource_modifiers": {
        "water_multiplier": 0.4,
        "glass_multiplier": 1.8,
        "salt_multiplier": 0.7,
        "rare_materials_chance": 1.2
      },
      "story_themes": [
        "lost_civilization",
        "technological_echoes",
        "archive_mysteries"
      ],
      "ambient_descriptions": {
        "entries": [
          {"item": "Glass-fused ruins stand as monuments to a lost age.", "weight": 3},
          {"item": "Ancient technology sleeps beneath layers of crystalline growth.", "weight": 3},
          {"item": "The walls remember voices that spoke here long ago.", "weight": 2},
          {"item": "Refracted light creates impossible geometries in the ruins.", "weight": 2},
          {"item": "Here, the past and present merge like light through a prism.", "weight": 1}
        ]
      }
    },
    {
      "id": "glass_gardens",
      "name": "Glass Gardens",
      "description": "Crystalline formations bloom like impossible flowers in the storm-touched earth",
      "environmental_features": [
        {
          "feature_type": "crystal_bloom",
          "weight": 35,
          "description_template": "Delicate glass formations spiral upward like frozen flowers",
          "mechanical_effects": {
            "visibility_modifier": 1.2,
            "refraction_gain": 2
          }
        },
        {
          "feature_type": "prism_grove",
          "weight": 25,
          "description_template": "A grove of prismatic spires refracts light into rainbows",
          "mechanical_effects": {
            "light_amplification": 1.5,
            "adaptation_trigger_chance": 0.15
          }
        },
        {
          "feature_type": "glass_vine",
          "weight": 20,
          "description_template": "Translucent vines of fused glass wind through the air",
          "mechanical_effects": {
            "movement_cost": 1.3,
            "damage_per_turn": 2
          }
        },
        {
          "feature_type": "mirror_pool",
          "weight": 15,
          "description_template": "A pool of liquid glass reflects distorted images",
          "mechanical_effects": {
            "vision_range_bonus": 2,
            "psychic_resonance": 0.3
          }
        },
        {
          "feature_type": "resonance_node",
          "weight": 5,
          "description_template": "A crystalline node hums with harmonic frequencies",
          "mechanical_effects": {
            "adaptation_acceleration": 1.5
          }
        }
      ],
      "atmospheric_elements": [
        {"element_type": "prismatic_light","intensity": 0.8,"description": "Light fractures into countless colors through the crystal formations.","triggers": ["high_light","clear_weather"]},
        {"element_type": "harmonic_resonance","intensity": 0.6,"description": "The air vibrates with crystalline harmonics.","triggers": ["high_light","clear_weather"]},
        {"element_type": "glass_pollen","intensity": 0.4,"description": "Microscopic glass particles drift on the breeze.","triggers": ["storm","high_refraction"]}
      ],
      "hazards": [
        {
          "hazard_type": "refraction_burn",
          "severity": 5,
          "description": "Concentrated light beams can cause severe burns",
          "trigger_conditions": ["high_light", "clear_weather"],
          "damage_range": [3, 8]
        },
        {
          "hazard_type": "glass_shard_storm",
          "severity": 7,
          "description": "Crystalline fragments whirl through the air",
          "trigger_conditions": ["storm_weather", "high_wind"],
          "damage_range": [5, 12]
        }
      ],
      "resource_modifiers": {
        "glass_multiplier": 2.5,
        "crystal_multiplier": 3.0,
        "rare_materials_chance": 1.8
      },
      "story_themes": [
        "beauty_and_danger",
        "transformation_through_light",
        "crystalline_consciousness"
      ],
      "ambient_descriptions": {
        "entries": [
          {"item": "Crystal formations bloom like impossible gardens of glass and light.", "weight": 3},
          {"item": "Prismatic spires cast rainbow shadows across the ground.", "weight": 3},
          {"item": "The air shimmers with refracted light and crystalline harmonics.", "weight": 2},
          {"item": "Glass vines twist through the air, beautiful and deadly.", "weight": 2},
          {"item": "Here, light itself seems to have taken root and grown.", "weight": 1}
        ]
      }
    },
    {
      "id": "shattered_citadel",
      "name": "Shattered Citadel",
      "description": "The broken remains of a great fortress, its walls fused into impossible geometries",
      "environmental_features": [
        {
          "feature_type": "twisted_spire",
          "weight": 30,
          "description_template": "A tower spirals impossibly upward, defying geometry",
          "mechanical_effects": {
            "visibility_modifier": 0.7,
            "navigation_difficulty": 1.4
          }
        },
        {
          "feature_type": "glass_rampart",
          "weight": 25,
          "description_template": "Crystalline battlements stretch across the broken landscape",
          "mechanical_effects": {
            "cover_bonus": 2,
            "defensive_position": true
          }
        },
        {
          "feature_type": "void_breach",
          "weight": 20,
          "description_template": "A tear in reality where the citadel once stood",
          "mechanical_effects": {
            "void_exposure": true,
            "psychic_damage": 3
          }
        },
        {
          "feature_type": "echo_chamber",
          "weight": 15,
          "description_template": "Sounds from the past still reverberate in these halls",
          "mechanical_effects": {
            "audio_distortion": 0.8,
            "memory_fragments": true
          }
        },
        {
          "feature_type": "throne_fragment",
          "weight": 10,
          "description_template": "Pieces of a great throne lie scattered and fused",
          "mechanical_effects": {
            "authority_resonance": 0.5,
            "faction_memory": true
          }
        }
      ],
      "atmospheric_elements": [
        {"element_type": "spectral_echoes","intensity": 0.9,"description": "Ghostly sounds of battle and ceremony echo through the ruins.","triggers": ["night","storm"]},
        {"element_type": "reality_distortion","intensity": 0.7,"description": "Space itself seems twisted and unreliable here.","triggers": ["storm","high_refraction"]},
        {"element_type": "temporal_fragments","intensity": 0.5,"description": "Glimpses of the past flicker at the edge of vision.","triggers": ["always"]}
      ],
      "hazards": [
        {
          "hazard_type": "reality_storm",
          "severity": 9,
          "description": "Tears in space-time create unpredictable dangers",
          "trigger_conditions": ["storm_weather", "high_refraction"],
          "damage_range": [8, 15]
        },
        {
          "hazard_type": "spectral_guardian",
          "severity": 7,
          "description": "Ghostly defenders still patrol these halls",
          "trigger_conditions": ["night_time", "trespassing"],
          "damage_range": [6, 10]
        }
      ],
      "resource_modifiers": {
        "ancient_tech_multiplier": 2.0,
        "void_essence_chance": 0.8,
        "rare_materials_chance": 1.5
      },
      "story_themes": [
        "fallen_glory",
        "temporal_echoes",
        "void_corruption"
      ],
      "ambient_descriptions": {
        "entries": [
          {"item": "The citadel's broken spires reach toward a sky they'll never touch again.", "weight": 3},
          {"item": "Glass-fused stone tells the story of the fortress's final moments.", "weight": 3},
          {"item": "Reality bends and warps around the ruins of ancient power.", "weight": 2},
          {"item": "Echoes of long-dead voices whisper through the twisted halls.", "weight": 2},
          {"item": "Here, the past refuses to stay buried.", "weight": 1}
        ]
      }
    },
    {
      "id": "salt_mines",
      "name": "Salt Mines",
      "description": "Deep excavations where crystalline salt was harvested before the storms came",
      "environmental_features": [
        {
          "feature_type": "salt_vein",
          "weight": 35,
          "description_template": "Thick veins of pure salt crystal run through the walls",
          "mechanical_effects": {
            "salt_harvest_bonus": 2.0,
            "dehydration_risk": 1.3
          }
        },
        {
          "feature_type": "mining_shaft",
          "weight": 25,
          "description_template": "A deep shaft descends into crystalline darkness",
          "mechanical_effects": {
            "vertical_movement": true,
            "fall_risk": 0.4
          }
        },
        {
          "feature_type": "brine_pool",
          "weight": 20,
          "description_template": "A pool of concentrated brine glows with inner light",
          "mechanical_effects": {
            "healing_source": 3,
            "corrosion_damage": 2
          }
        },
        {
          "feature_type": "crystal_chamber",
          "weight": 15,
          "description_template": "A natural chamber lined with salt crystals",
          "mechanical_effects": {
            "acoustic_amplification": 1.5,
            "crystal_resonance": 0.6
          }
        },
        {
          "feature_type": "collapsed_tunnel",
          "weight": 5,
          "description_template": "A tunnel blocked by fallen salt and stone",
          "mechanical_effects": {
            "excavation_required": true,
            "hidden_passage": 0.3
          }
        }
      ],
      "atmospheric_elements": [
        {"element_type": "salt_dust","intensity": 0.8,"description": "Fine salt particles fill the air, making breathing difficult.","triggers": ["always"]},
        {"element_type": "crystalline_echoes","intensity": 0.6,"description": "Every sound reverberates through the crystal-lined tunnels.","triggers": ["always"]},
        {"element_type": "brine_vapors","intensity": 0.4,"description": "Corrosive vapors rise from pools of concentrated salt water.","triggers": ["always"]}
      ],
      "hazards": [
        {
          "hazard_type": "salt_lung",
          "severity": 5,
          "description": "Prolonged exposure causes respiratory damage",
          "trigger_conditions": ["extended_stay", "heavy_breathing"],
          "damage_range": [2, 5]
        },
        {
          "hazard_type": "tunnel_collapse",
          "severity": 7,
          "description": "Unstable tunnels may cave in without warning",
          "trigger_conditions": ["loud_noise", "structural_damage"],
          "damage_range": [8, 20]
        }
      ],
      "resource_modifiers": {
        "salt_multiplier": 4.0,
        "brine_multiplier": 3.0,
        "crystal_multiplier": 1.5
      },
      "story_themes": [
        "industrial_heritage",
        "underground_mysteries",
        "crystalline_preservation"
      ],
      "ambient_descriptions": {
        "entries": [
          {"item": "Salt crystals line the tunnel walls like frozen tears.", "weight": 3},
          {"item": "The air tastes of brine and ancient labor.", "weight": 3},
          {"item": "Mining equipment lies abandoned, preserved in salt.", "weight": 2},
          {"item": "Deep shafts descend into crystalline darkness.", "weight": 2},
          {"item": "Here, the earth's bones are made of salt.", "weight": 1}
        ]
      }
    },
    {
      "id": "storm_scars",
      "name": "Storm Scars",
      "description": "Twisted landscapes where glass storms have repeatedly carved and recarved the earth",
      "environmental_features": [
        {
          "feature_type": "glass_canyon",
          "weight": 30,
          "description_template": "A deep canyon carved by concentrated storm winds",
          "mechanical_effects": {
            "wind_amplification": 2.0,
            "navigation_difficulty": 1.6
          }
        },
        {
          "feature_type": "storm_spiral",
          "weight": 25,
          "description_template": "The ground spirals in patterns matching ancient storm paths",
          "mechanical_effects": {
            "disorientation": 0.7,
            "storm_prediction_bonus": 1.3
          }
        },
        {
          "feature_type": "glass_mesa",
          "weight": 20,
          "description_template": "A flat-topped hill of fused glass and stone",
          "mechanical_effects": {
            "elevation_bonus": 3,
            "lightning_attraction": 1.5
          }
        },
        {
          "feature_type": "wind_tunnel",
          "weight": 15,
          "description_template": "A natural tunnel carved by perpetual winds",
          "mechanical_effects": {
            "movement_acceleration": 1.4,
            "sound_distortion": 0.8
          }
        },
        {
          "feature_type": "storm_eye_remnant",
          "weight": 10,
          "description_template": "A perfectly circular area of unnatural calm",
          "mechanical_effects": {
            "storm_immunity": true,
            "temporal_distortion": 0.3
          }
        }
      ],
      "atmospheric_elements": [
        {"element_type": "perpetual_wind","intensity": 0.9,"description": "Constant winds howl through the scarred landscape.","triggers": ["always","storm"]},
        {"element_type": "glass_dust_devils","intensity": 0.7,"description": "Miniature whirlwinds of glass particles dance across the ground.","triggers": ["always"]},
        {"element_type": "storm_memory","intensity": 0.5,"description": "The very air seems to remember the fury of past storms.","triggers": ["always"]}
      ],
      "hazards": [
        {
          "hazard_type": "glass_tornado",
          "severity": 9,
          "description": "Whirlwinds of razor-sharp glass fragments",
          "trigger_conditions": ["high_wind", "storm_weather"],
          "damage_range": [10, 25]
        },
        {
          "hazard_type": "wind_shear",
          "severity": 5,
          "description": "Sudden changes in wind direction can knock travelers down",
          "trigger_conditions": ["exposed_position", "high_wind"],
          "damage_range": [3, 8]
        }
      ],
      "resource_modifiers": {
        "storm_glass_multiplier": 3.5,
        "wind_essence_chance": 1.2,
        "rare_materials_chance": 1.4
      },
      "story_themes": [
        "natural_fury",
        "storm_worship",
        "elemental_scars"
      ],
      "ambient_descriptions": {
        "entries": [
          {"item": "The landscape bears the scars of countless glass storms.", "weight": 3},
          {"item": "Wind-carved canyons spiral in impossible patterns.", "weight": 3},
          {"item": "The very ground remembers the fury of ancient tempests.", "weight": 2},
          {"item": "Glass mesas rise like monuments to elemental power.", "weight": 2},
          {"item": "Here, the storms have written their history in stone and glass.", "weight": 1}
        ]
      }
    },
    {
      "id": "refraction_fields",
      "name": "Refraction Fields",
      "description": "Vast expanses where light bends and reality becomes uncertain",
      "environmental_features": [
        {
          "feature_type": "light_maze",
          "weight": 30,
          "description_template": "Beams of light create a labyrinth of illumination",
          "mechanical_effects": {
            "navigation_difficulty": 2.0,
            "light_based_puzzles": true
          }
        },
        {
          "feature_type": "mirage_oasis",
          "weight": 25,
          "description_template": "An illusory oasis shimmers in the distance",
          "mechanical_effects": {
            "false_destination": true,
            "hope_and_despair": 0.8
          }
        },
        {
          "feature_type": "prism_field",
          "weight": 20,
          "description_template": "Countless small prisms scatter light in all directions",
          "mechanical_effects": {
            "visibility_chaos": 1.5,
            "rainbow_effects": true
          }
        },
        {
          "feature_type": "reflection_pool",
          "weight": 15,
          "description_template": "A pool that reflects things that aren't there",
          "mechanical_effects": {
            "false_visions": 0.6,
            "prophetic_glimpses": 0.2
          }
        },
        {
          "feature_type": "light_fountain",
          "weight": 10,
          "description_template": "Pure light erupts from the ground like water",
          "mechanical_effects": {
            "light_source": 5,
            "adaptation_catalyst": 1.8
          }
        }
      ],
      "atmospheric_elements": [
        {"element_type": "reality_distortion","intensity": 0.9,"description": "Light bends in impossible ways, making navigation treacherous.","triggers": ["storm","high_refraction"]},
        {"element_type": "optical_illusions","intensity": 0.8,"description": "Nothing is quite what it seems in this place.","triggers": ["always"]},
        {"element_type": "chromatic_aberration","intensity": 0.6,"description": "Colors separate and recombine in strange patterns.","triggers": ["always"]}
      ],
      "hazards": [
        {
          "hazard_type": "light_burn",
          "severity": 7,
          "description": "Concentrated light beams can cause severe damage",
          "trigger_conditions": ["direct_exposure", "high_refraction"],
          "damage_range": [6, 12]
        },
        {
          "hazard_type": "optical_madness",
          "severity": 5,
          "description": "Prolonged exposure to impossible sights affects the mind",
          "trigger_conditions": ["extended_stay", "high_adaptation"],
          "damage_range": [2, 6]
        }
      ],
      "resource_modifiers": {
        "light_essence_multiplier": 4.0,
        "prism_multiplier": 2.5,
        "rare_materials_chance": 2.0
      },
      "story_themes": [
        "perception_and_reality",
        "light_as_substance",
        "optical_mysteries"
      ],
      "ambient_descriptions": {
        "entries": [
          {"item": "Light bends and flows like liquid through the air.", "weight": 3},
          {"item": "Reality becomes negotiable in the presence of so much refracted light.", "weight": 3},
          {"item": "Mirages and true visions blend until distinction becomes meaningless.", "weight": 2},
          {"item": "The very air shimmers with prismatic possibilities.", "weight": 2},
          {"item": "Here, light has learned to lie.", "weight": 1}
        ]
      }
    }
  ]
}
